student_management/__init__.py
student_management/main.py
student_management/main_window.py
student_management/config/__init__.py
student_management/config/cfg.py
student_management/db/__init__.py
student_management/db/connection.py
student_management/dialogs/__init__.py
student_management/dialogs/about_dialog.py
student_management/dialogs/delete_dialog.py
student_management/dialogs/edit_dialog.py
student_management/dialogs/insert_dialog.py
student_management/dialogs/search_dialog.py
student_management_lt-0.0.8.dist-info/METADATA
student_management_lt-0.0.8.dist-info/WHEEL
student_management_lt-0.0.8.dist-info/entry_points.txt
student_management_lt-0.0.8.dist-info/top_level.txt
student_management_lt-0.0.8.dist-info/RECORD
