Metadata-Version: 2.4
Name: student-management-lt
Version: 0.0.8
Summary: A desktop PyQt6 GUI app for managing university student data with an SQL database backend.
Home-page: https://github.com/ltuala/student-management
Author: Lyndon Tuala
Author-email: lyndontuala@gmail.com
Project-URL: Bug Reports, https://github.com/ltuala/student-management/issues
Project-URL: Source, https://github.com/ltuala/student-management/
Classifier: Development Status :: 3 - Alpha
Classifier: Intended Audience :: Developers
Classifier: License :: OSI Approved :: MIT License
Classifier: Programming Language :: Python :: 3
Classifier: Programming Language :: Python :: 3.7
Classifier: Programming Language :: Python :: 3.8
Classifier: Programming Language :: Python :: 3.9
Classifier: Programming Language :: Python :: 3.10
Requires-Dist: PyQt6
Requires-Dist: python-dotenv
Dynamic: author
Dynamic: author-email
Dynamic: classifier
Dynamic: description
Dynamic: description-content-type
Dynamic: home-page
Dynamic: project-url
Dynamic: requires-dist
Dynamic: summary
